fps_limiter/__init__.py
fps_limiter-0.1.1.dist-info/DESCRIPTION.rst
fps_limiter-0.1.1.dist-info/METADATA
fps_limiter-0.1.1.dist-info/RECORD
fps_limiter-0.1.1.dist-info/WHEEL
fps_limiter-0.1.1.dist-info/metadata.json
fps_limiter-0.1.1.dist-info/top_level.txt
